{"version": "5.0.1", "flags": {}, "shapes": [{"label": "Line", "points": [[350.0, 1920.0], [342.0, 1870.0], [336.0, 1820.0], [342.0, 1770.0], [380.0, 1720.0], [405.0, 1670.0], [364.0, 1620.0], [390.0, 1570.0], [394.0, 1520.0], [890.71875, 1470.0], [592.0, 1520.0], [595.0, 1570.0], [575.0, 1620.0], [623.0, 1670.0], [604.0, 1720.0], [573.0, 1770.0], [573.0, 1820.0], [586.0, 1870.0], [600.0, 1920.0]], "group_id": null, "shape_type": "polygon", "flags": {}}], "imagePath": "frame116.jpg", "imageData": null, "imageHeight": 1920, "imageWidth": 1080}